{
  "quotes": [
    {
      "date": "2026-02-16",
      "content": "理性的人追求的并非快乐，而只是避免痛苦。",
      "author": "叔本华"
    },
    {
      "date": "2026-02-15",
      "content": "一点星光，在心上就能反射出太阳。",
      "author": "学而思"
    },
    {
      "date": "2026-02-14",
      "content": "行百里者半九十。",
      "author": "战国策·秦策五·谓秦王"
    },
    {
      "date": "2026-02-13",
      "content": "从来不会生气的人，注定终生遭受欺凌和压制，直至被摧毁和消灭。",
      "author": "M·斯科特·派克"
    },
    {
      "date": "2026-02-12",
      "content": "不管人生呈现出什么样貌，人生的构成要素都是一样的。",
      "author": "叔本华"
    },
    {
      "date": "2026-02-11",
      "content": "我们把世界看错，反说它欺骗了我们。",
      "author": "泰戈尔"
    },
    {
      "date": "2026-02-10",
      "content": "剃刀边缘怎能起造伽蓝。",
      "author": "木心"
    },
    {
      "date": "2026-02-09",
      "content": "认真的思索，真诚的明辨是非，有这种态度，大概可算是善良吧。",
      "author": "王小波"
    },
    {
      "date": "2026-02-08",
      "content": "遗忘比绝望更强有力。",
      "author": "叔本华"
    },
    {
      "date": "2026-02-07",
      "content": "哲学的基本问题是思维和存在的关系问题。",
      "author": "哲学的基本问题"
    },
    {
      "date": "2026-02-06",
      "content": "世界是一场空虚的宇宙，有时候仍像是一个梦。",
      "author": "小冰"
    },
    {
      "date": "2026-02-05",
      "content": "认真的思索，真诚的明辨是非，有这种态度，大概可算是善良吧。",
      "author": "王小波"
    },
    {
      "date": "2026-02-04",
      "content": "且视他人之疑目如盏盏鬼火，大胆地去你的夜路。",
      "author": "史铁生"
    },
    {
      "date": "2026-02-03",
      "content": "最折磨人的或许不是一场惨烈战争，而是烦琐的日常生活。",
      "author": "亦舒"
    },
    {
      "date": "2026-02-02",
      "content": "爱欲于人，犹如执炬，逆风而行，必有烧手之患。",
      "author": "四十二章经"
    },
    {
      "date": "2026-02-01",
      "content": "行远自迩，登高自卑。",
      "author": "戴圣"
    },
    {
      "date": "2026-01-31",
      "content": "无垢清净光，慧日破诸暗，能伏灾风火，普明照世间。",
      "author": "鸠摩罗什"
    },
    {
      "date": "2026-01-30",
      "content": "遗忘比绝望更强有力。",
      "author": "叔本华"
    },
    {
      "date": "2026-01-29",
      "content": "甲之蜜糖，乙之砒霜。",
      "author": "亦舒"
    },
    {
      "date": "2026-01-28",
      "content": "师者，所以传道授业解惑也。",
      "author": "韩愈"
    },
    {
      "date": "2026-01-27",
      "content": "因为不可能，所以才值得相信。",
      "author": "歌德"
    },
    {
      "date": "2026-01-26",
      "content": "博学而笃志，切问而近思。",
      "author": "论语·子张"
    },
    {
      "date": "2026-01-25",
      "content": "哲学家们只是用不同的方式解释世界，而问题在于改变世界。",
      "author": "马克思"
    },
    {
      "date": "2026-01-24",
      "content": "忘掉一个人的劣根性就像把千辛万苦赚来的钱扔掉一样。",
      "author": "叔本华"
    },
    {
      "date": "2026-01-23",
      "content": "纵然变化，依然故我。",
      "author": "雅各布·伯努利"
    },
    {
      "date": "2026-01-22",
      "content": "爱欲于人，犹如执炬，逆风而行，必有烧手之患。",
      "author": "四十二章经"
    },
    {
      "date": "2026-01-21",
      "content": "似水流年是一个人所有的一切，只有这个东西，才真正归你所有。",
      "author": "王小波"
    },
    {
      "date": "2026-01-20",
      "content": "一个人的自身越是丰富，就越难以忍受世俗常规的安排。",
      "author": "叔本华"
    },
    {
      "date": "2026-01-19",
      "content": "生活中最重要的不是凯旋，而是奋斗。",
      "author": "人民日报"
    },
    {
      "date": "2026-01-18",
      "content": "那些听不见音乐的人以为跳舞的人疯了。",
      "author": "弗里德里希·威廉·尼采"
    }
  ]
}